odoo8_addon_board_frontdesk-8.0.1.0.0-py2.7-nspkg.pth
odoo_addons/board_frontdesk/__openerp__.py
odoo_addons/board_frontdesk/board_frontdesk_view.xml
odoo_addons/board_frontdesk/__init__.py
odoo_addons/board_frontdesk/i18n/es.po
odoo_addons/board_frontdesk/i18n/board_frontdesk.pot
odoo_addons/board_frontdesk/i18n/sv.po
odoo_addons/board_frontdesk/i18n/fi.po
odoo_addons/board_frontdesk/i18n/fr_BE.po
odoo8_addon_board_frontdesk-8.0.1.0.0.dist-info/top_level.txt
odoo8_addon_board_frontdesk-8.0.1.0.0.dist-info/WHEEL
odoo8_addon_board_frontdesk-8.0.1.0.0.dist-info/RECORD
odoo8_addon_board_frontdesk-8.0.1.0.0.dist-info/metadata.json
odoo8_addon_board_frontdesk-8.0.1.0.0.dist-info/DESCRIPTION.rst
odoo8_addon_board_frontdesk-8.0.1.0.0.dist-info/METADATA
odoo8_addon_board_frontdesk-8.0.1.0.0.dist-info/namespace_packages.txt
