Metadata-Version: 2.0
Name: odoo8-addon-board-frontdesk
Version: 8.0.1.0.0
Summary: Board for Hotel FrontDesk
Home-page: UNKNOWN
Author: UNKNOWN
Author-email: UNKNOWN
License: UNKNOWN
Platform: UNKNOWN
Requires-Dist: odoo (<9.0a,>=8.0a)
Requires-Dist: odoo8-addon-report-hotel-reservation
Classifier: Programming Language :: Python :: 2.7
Classifier: Framework :: Odoo
